conflore/__init__.py
conflore/conflore.py
conflore/io.py
conflore-0.2.2.dist-info/METADATA
conflore-0.2.2.dist-info/WHEEL
conflore-0.2.2.dist-info/RECORD
