Metadata-Version: 2.3
Name: conflore
Version: 0.2.2
Summary: Load and save configurations in a simple way.
License: MIT
Author: Likianta
Author-email: likianta@foxmail.com
Requires-Python: >=3.8
Classifier: License :: OSI Approved :: MIT License
Classifier: Programming Language :: Python :: 3
Classifier: Programming Language :: Python :: 3.8
Classifier: Programming Language :: Python :: 3.9
Classifier: Programming Language :: Python :: 3.10
Classifier: Programming Language :: Python :: 3.11
Classifier: Programming Language :: Python :: 3.12
Classifier: Programming Language :: Python :: 3.13
Provides-Extra: yml
Requires-Dist: pyyaml ; extra == "yml"
